[
null,
{"id":1,"list":[{"code":111,"indent":0,"parameters":[12,"uAPI.isBattle == true"]},{"code":355,"indent":1,"parameters":["uAPI.show"]},{"code":134,"indent":1,"parameters":[0]},{"code":0,"indent":1,"parameters":[]},{"code":411,"indent":0,"parameters":[]},{"code":355,"indent":1,"parameters":["uAPI.hide"]},{"code":134,"indent":1,"parameters":[1]},{"code":0,"indent":1,"parameters":[]},{"code":412,"indent":0,"parameters":[]},{"code":0,"indent":0,"parameters":[]}],"name":"PODCZAS WALKI","switchId":1,"trigger":2},
{"id":2,"list":[{"code":356,"indent":0,"parameters":["fast_travel"]},{"code":0,"indent":0,"parameters":[]}],"name":"FAST TRAVEL","switchId":1,"trigger":0},
{"id":3,"list":[{"code":111,"indent":0,"parameters":[1,14,0,0,0]},{"code":230,"indent":1,"parameters":[360]},{"code":223,"indent":1,"parameters":[[-68,-68,0,68],60,false]},{"code":122,"indent":1,"parameters":[14,14,0,0,1]},{"code":0,"indent":1,"parameters":[]},{"code":412,"indent":0,"parameters":[]},{"code":111,"indent":0,"parameters":[1,14,0,1,0]},{"code":230,"indent":1,"parameters":[360]},{"code":223,"indent":1,"parameters":[[-68,-68,0,68],60,false]},{"code":122,"indent":1,"parameters":[14,14,0,0,2]},{"code":0,"indent":1,"parameters":[]},{"code":412,"indent":0,"parameters":[]},{"code":111,"indent":0,"parameters":[1,14,0,2,0]},{"code":230,"indent":1,"parameters":[360]},{"code":223,"indent":1,"parameters":[[-68,-68,0,68],60,false]},{"code":122,"indent":1,"parameters":[14,14,0,0,3]},{"code":0,"indent":1,"parameters":[]},{"code":412,"indent":0,"parameters":[]},{"code":111,"indent":0,"parameters":[1,14,0,3,0]},{"code":230,"indent":1,"parameters":[360]},{"code":223,"indent":1,"parameters":[[-34,-34,0,68],60,false]},{"code":122,"indent":1,"parameters":[14,14,0,0,4]},{"code":0,"indent":1,"parameters":[]},{"code":412,"indent":0,"parameters":[]},{"code":111,"indent":0,"parameters":[1,14,0,4,0]},{"code":230,"indent":1,"parameters":[360]},{"code":223,"indent":1,"parameters":[[-17,-17,0,68],60,false]},{"code":122,"indent":1,"parameters":[14,14,0,0,5]},{"code":0,"indent":1,"parameters":[]},{"code":412,"indent":0,"parameters":[]},{"code":111,"indent":0,"parameters":[1,14,0,5,0]},{"code":230,"indent":1,"parameters":[360]},{"code":223,"indent":1,"parameters":[[0,0,0,40],60,false]},{"code":122,"indent":1,"parameters":[14,14,0,0,6]},{"code":0,"indent":1,"parameters":[]},{"code":412,"indent":0,"parameters":[]},{"code":111,"indent":0,"parameters":[1,14,0,6,0]},{"code":230,"indent":1,"parameters":[360]},{"code":223,"indent":1,"parameters":[[0,0,0,0],60,false]},{"code":122,"indent":1,"parameters":[14,14,0,0,7]},{"code":0,"indent":1,"parameters":[]},{"code":412,"indent":0,"parameters":[]},{"code":111,"indent":0,"parameters":[1,14,0,7,0]},{"code":230,"indent":1,"parameters":[360]},{"code":223,"indent":1,"parameters":[[0,0,0,0],60,false]},{"code":122,"indent":1,"parameters":[14,14,0,0,8]},{"code":0,"indent":1,"parameters":[]},{"code":412,"indent":0,"parameters":[]},{"code":111,"indent":0,"parameters":[1,14,0,8,0]},{"code":230,"indent":1,"parameters":[360]},{"code":223,"indent":1,"parameters":[[0,0,0,0],60,false]},{"code":122,"indent":1,"parameters":[14,14,0,0,9]},{"code":0,"indent":1,"parameters":[]},{"code":412,"indent":0,"parameters":[]},{"code":111,"indent":0,"parameters":[1,14,0,9,0]},{"code":230,"indent":1,"parameters":[360]},{"code":223,"indent":1,"parameters":[[0,0,0,0],60,false]},{"code":122,"indent":1,"parameters":[14,14,0,0,10]},{"code":0,"indent":1,"parameters":[]},{"code":412,"indent":0,"parameters":[]},{"code":111,"indent":0,"parameters":[1,14,0,10,0]},{"code":230,"indent":1,"parameters":[360]},{"code":223,"indent":1,"parameters":[[0,0,0,0],60,false]},{"code":122,"indent":1,"parameters":[14,14,0,0,11]},{"code":0,"indent":1,"parameters":[]},{"code":412,"indent":0,"parameters":[]},{"code":111,"indent":0,"parameters":[1,14,0,11,0]},{"code":230,"indent":1,"parameters":[360]},{"code":223,"indent":1,"parameters":[[0,0,0,0],60,false]},{"code":122,"indent":1,"parameters":[14,14,0,0,12]},{"code":0,"indent":1,"parameters":[]},{"code":412,"indent":0,"parameters":[]},{"code":111,"indent":0,"parameters":[1,14,0,12,0]},{"code":230,"indent":1,"parameters":[360]},{"code":223,"indent":1,"parameters":[[0,0,0,0],60,false]},{"code":122,"indent":1,"parameters":[14,14,0,0,13]},{"code":0,"indent":1,"parameters":[]},{"code":412,"indent":0,"parameters":[]},{"code":111,"indent":0,"parameters":[1,14,0,13,0]},{"code":230,"indent":1,"parameters":[360]},{"code":223,"indent":1,"parameters":[[0,0,0,0],60,false]},{"code":122,"indent":1,"parameters":[14,14,0,0,14]},{"code":0,"indent":1,"parameters":[]},{"code":412,"indent":0,"parameters":[]},{"code":111,"indent":0,"parameters":[1,14,0,14,0]},{"code":230,"indent":1,"parameters":[360]},{"code":223,"indent":1,"parameters":[[0,0,0,0],60,false]},{"code":122,"indent":1,"parameters":[14,14,0,0,15]},{"code":0,"indent":1,"parameters":[]},{"code":412,"indent":0,"parameters":[]},{"code":111,"indent":0,"parameters":[1,14,0,15,0]},{"code":230,"indent":1,"parameters":[360]},{"code":223,"indent":1,"parameters":[[0,0,0,0],60,false]},{"code":122,"indent":1,"parameters":[14,14,0,0,16]},{"code":0,"indent":1,"parameters":[]},{"code":412,"indent":0,"parameters":[]},{"code":111,"indent":0,"parameters":[1,14,0,16,0]},{"code":230,"indent":1,"parameters":[360]},{"code":223,"indent":1,"parameters":[[0,0,0,0],60,false]},{"code":122,"indent":1,"parameters":[14,14,0,0,17]},{"code":0,"indent":1,"parameters":[]},{"code":412,"indent":0,"parameters":[]},{"code":111,"indent":0,"parameters":[1,14,0,17,0]},{"code":230,"indent":1,"parameters":[360]},{"code":223,"indent":1,"parameters":[[0,0,0,20],60,false]},{"code":122,"indent":1,"parameters":[14,14,0,0,18]},{"code":0,"indent":1,"parameters":[]},{"code":412,"indent":0,"parameters":[]},{"code":111,"indent":0,"parameters":[1,14,0,18,0]},{"code":230,"indent":1,"parameters":[360]},{"code":223,"indent":1,"parameters":[[-20,-20,0,40],60,false]},{"code":122,"indent":1,"parameters":[14,14,0,0,19]},{"code":0,"indent":1,"parameters":[]},{"code":412,"indent":0,"parameters":[]},{"code":111,"indent":0,"parameters":[1,14,0,19,0]},{"code":230,"indent":1,"parameters":[360]},{"code":223,"indent":1,"parameters":[[-40,-50,0,60],60,false]},{"code":122,"indent":1,"parameters":[14,14,0,0,20]},{"code":0,"indent":1,"parameters":[]},{"code":412,"indent":0,"parameters":[]},{"code":111,"indent":0,"parameters":[1,14,0,20,0]},{"code":230,"indent":1,"parameters":[360]},{"code":223,"indent":1,"parameters":[[-68,-68,0,68],60,false]},{"code":122,"indent":1,"parameters":[14,14,0,0,21]},{"code":0,"indent":1,"parameters":[]},{"code":412,"indent":0,"parameters":[]},{"code":111,"indent":0,"parameters":[1,14,0,21,0]},{"code":230,"indent":1,"parameters":[360]},{"code":223,"indent":1,"parameters":[[-68,-68,0,68],60,false]},{"code":122,"indent":1,"parameters":[14,14,0,0,22]},{"code":0,"indent":1,"parameters":[]},{"code":412,"indent":0,"parameters":[]},{"code":111,"indent":0,"parameters":[1,14,0,22,0]},{"code":230,"indent":1,"parameters":[360]},{"code":223,"indent":1,"parameters":[[-68,-68,0,68],60,false]},{"code":122,"indent":1,"parameters":[14,14,0,0,23]},{"code":0,"indent":1,"parameters":[]},{"code":412,"indent":0,"parameters":[]},{"code":111,"indent":0,"parameters":[1,14,0,23,0]},{"code":230,"indent":1,"parameters":[360]},{"code":223,"indent":1,"parameters":[[-68,-68,0,119],60,false]},{"code":122,"indent":1,"parameters":[14,14,0,0,0]},{"code":0,"indent":1,"parameters":[]},{"code":412,"indent":0,"parameters":[]},{"code":0,"indent":0,"parameters":[]}],"name":"Czas","switchId":14,"trigger":2},
{"id":4,"list":[{"code":231,"indent":0,"parameters":[1,"Ogłoszenie",0,0,300,-200,100,100,255,0]},{"code":101,"indent":0,"parameters":["",0,2,2]},{"code":401,"indent":0,"parameters":[""]},{"code":235,"indent":0,"parameters":[1]},{"code":126,"indent":0,"parameters":[6,0,0,1]},{"code":0,"indent":0,"parameters":[]}],"name":"Ator","switchId":1,"trigger":0},
{"id":5,"list":[{"code":0,"indent":0,"parameters":[]}],"name":"","switchId":1,"trigger":0},
{"id":6,"list":[{"code":0,"indent":0,"parameters":[]}],"name":"","switchId":1,"trigger":0},
{"id":7,"list":[{"code":122,"indent":0,"parameters":[25,25,1,0,1]},{"code":111,"indent":0,"parameters":[1,25,0,23,0]},{"code":355,"indent":1,"parameters":["uAPI.isBattle"]},{"code":201,"indent":1,"parameters":[0,76,47,42,4,0]},{"code":121,"indent":1,"parameters":[44,44,0]},{"code":121,"indent":1,"parameters":[16,16,0]},{"code":230,"indent":1,"parameters":[60]},{"code":101,"indent":1,"parameters":["",0,0,2]},{"code":401,"indent":1,"parameters":["Dziękuje ci za pomoc"]},{"code":101,"indent":1,"parameters":["",0,0,2]},{"code":401,"indent":1,"parameters":["Twoje ziemie są już czyste od ludzi"]},{"code":205,"indent":1,"parameters":[256,{"list":[{"code":4,"indent":null},{"code":2,"indent":null},{"code":2,"indent":null},{"code":4,"indent":null},{"code":4,"indent":null},{"code":0}],"repeat":false,"skippable":false,"wait":true}]},{"code":505,"indent":1,"parameters":[{"code":4,"indent":null}]},{"code":505,"indent":1,"parameters":[{"code":2,"indent":null}]},{"code":505,"indent":1,"parameters":[{"code":2,"indent":null}]},{"code":505,"indent":1,"parameters":[{"code":4,"indent":null}]},{"code":505,"indent":1,"parameters":[{"code":4,"indent":null}]},{"code":121,"indent":1,"parameters":[45,45,0]},{"code":123,"indent":1,"parameters":["C",0]},{"code":0,"indent":1,"parameters":[]},{"code":411,"indent":0,"parameters":[]},{"code":123,"indent":1,"parameters":["C",0]},{"code":0,"indent":1,"parameters":[]},{"code":412,"indent":0,"parameters":[]},{"code":0,"indent":0,"parameters":[]}],"name":"SABOTAŻ SzyrgolToKox1","switchId":1,"trigger":0},
{"id":8,"list":[{"code":205,"indent":0,"parameters":[-1,{"list":[{"code":3,"indent":null},{"code":19,"indent":null},{"code":0}],"repeat":false,"skippable":false,"wait":true}]},{"code":505,"indent":0,"parameters":[{"code":3,"indent":null}]},{"code":505,"indent":0,"parameters":[{"code":19,"indent":null}]},{"code":205,"indent":0,"parameters":[30,{"list":[{"code":1,"indent":null},{"code":1,"indent":null},{"code":1,"indent":null},{"code":1,"indent":null},{"code":1,"indent":null},{"code":1,"indent":null},{"code":1,"indent":null},{"code":1,"indent":null},{"code":1,"indent":null},{"code":1,"indent":null},{"code":1,"indent":null},{"code":1,"indent":null},{"code":0}],"repeat":false,"skippable":true,"wait":true}]},{"code":505,"indent":0,"parameters":[{"code":1,"indent":null}]},{"code":505,"indent":0,"parameters":[{"code":1,"indent":null}]},{"code":505,"indent":0,"parameters":[{"code":1,"indent":null}]},{"code":505,"indent":0,"parameters":[{"code":1,"indent":null}]},{"code":505,"indent":0,"parameters":[{"code":1,"indent":null}]},{"code":505,"indent":0,"parameters":[{"code":1,"indent":null}]},{"code":505,"indent":0,"parameters":[{"code":1,"indent":null}]},{"code":505,"indent":0,"parameters":[{"code":1,"indent":null}]},{"code":505,"indent":0,"parameters":[{"code":1,"indent":null}]},{"code":505,"indent":0,"parameters":[{"code":1,"indent":null}]},{"code":505,"indent":0,"parameters":[{"code":1,"indent":null}]},{"code":505,"indent":0,"parameters":[{"code":1,"indent":null}]},{"code":101,"indent":0,"parameters":["",0,1,2]},{"code":401,"indent":0,"parameters":["\\auto \\msgevent[30] Witaj"]},{"code":101,"indent":0,"parameters":["",0,1,2]},{"code":401,"indent":0,"parameters":["\\auto \\msgevent[0] Witaj..."]},{"code":101,"indent":0,"parameters":["",0,1,2]},{"code":401,"indent":0,"parameters":["\\auto \\msgevent[30] Już bardzo dawno nikt z zewnątrz "]},{"code":401,"indent":0,"parameters":["nasz nie odwiedzał.                                                           "]},{"code":401,"indent":0,"parameters":["                      "]},{"code":401,"indent":0,"parameters":["                          "]},{"code":213,"indent":0,"parameters":[30,9,false]},{"code":101,"indent":0,"parameters":["",0,1,2]},{"code":401,"indent":0,"parameters":["\\auto \\msgevent[0] co cię tak zdziwiło"]},{"code":101,"indent":0,"parameters":["",0,1,2]},{"code":401,"indent":0,"parameters":["\\auto \\msgevent[30] Jeżeli tu jesteś to znaczy...."]},{"code":401,"indent":0,"parameters":["               ...że...                                                      "]},{"code":401,"indent":0,"parameters":["                                ...pokonałeś torrena."]},{"code":101,"indent":0,"parameters":["",0,1,2]},{"code":401,"indent":0,"parameters":["\\auto \\msgevent[0] Chodzi ci o tą przrośniętą skałe "]},{"code":101,"indent":0,"parameters":["",0,1,2]},{"code":401,"indent":0,"parameters":["\\auto \\msgevent[30] TO NIE JEST ŻADANA PRZEROŚNIĘTA"]},{"code":401,"indent":0,"parameters":["SKAŁA!!!                    "]},{"code":401,"indent":0,"parameters":["to nasz strażnik, nie nazywj go W TEN SPOSUB!!!"]},{"code":101,"indent":0,"parameters":["",0,1,2]},{"code":401,"indent":0,"parameters":["\\auto \\msgevent[0] To dla."]},{"code":250,"indent":0,"parameters":[{"name":"Attack1","volume":90,"pitch":100,"pan":0}]},{"code":101,"indent":0,"parameters":["",0,1,2]},{"code":401,"indent":0,"parameters":["\\auto \\msgevent[30] Dlaczego Tak się ucieszyłam że go "]},{"code":401,"indent":0,"parameters":["zgłodziłeś =)."]},{"code":101,"indent":0,"parameters":["",0,1,2]},{"code":401,"indent":0,"parameters":["\\auto \\msgevent[0] Tak właśnie. "]},{"code":101,"indent":0,"parameters":["",0,1,2]},{"code":401,"indent":0,"parameters":["\\auto \\msgevent[0] Po pierwsz z "]},{"code":250,"indent":0,"parameters":[{"name":"Attack1","volume":90,"pitch":100,"pan":0}]},{"code":101,"indent":0,"parameters":["",0,1,2]},{"code":401,"indent":0,"parameters":["\\auto \\msgevent[30] kąd widziałam Co chcaiłeś "]},{"code":401,"indent":0,"parameters":["powiedzieć."]},{"code":213,"indent":0,"parameters":[-1,7,false]},{"code":250,"indent":0,"parameters":[{"name":"Down2","volume":90,"pitch":100,"pan":0}]},{"code":101,"indent":0,"parameters":["",0,1,2]},{"code":401,"indent":0,"parameters":["\\auto \\msgevent[30] Jestem medium tej wioski."]},{"code":213,"indent":0,"parameters":[-1,7,false]},{"code":101,"indent":0,"parameters":["",0,1,2]},{"code":401,"indent":0,"parameters":["\\auto \\msgevent[30] chcesz odpoweidz na twoje drugie "]},{"code":401,"indent":0,"parameters":["pytanie?"]},{"code":101,"indent":0,"parameters":["",0,1,2]},{"code":401,"indent":0,"parameters":["\\auto \\msgevent[0] Jak mniemam znasz jak one brzmi. "]},{"code":250,"indent":0,"parameters":[{"name":"Attack1","volume":90,"pitch":100,"pan":0}]},{"code":101,"indent":0,"parameters":["",0,1,2]},{"code":401,"indent":0,"parameters":["\\auto \\msgevent[30] Oczywiście"]},{"code":101,"indent":0,"parameters":["",0,1,2]},{"code":401,"indent":0,"parameters":["\\auto \\msgevent[0] To odpowiadaj."]},{"code":101,"indent":0,"parameters":["",0,0,1]},{"code":401,"indent":0,"parameters":["Dla niekumatych, drugie pytanie brzmi "]},{"code":401,"indent":0,"parameters":["\"Dlaczego uczieszyłaś się jak zgłdziłem waszego "]},{"code":401,"indent":0,"parameters":["strażnika\""]},{"code":101,"indent":0,"parameters":["",0,1,2]},{"code":401,"indent":0,"parameters":["\\auto \\msgevent[30] Poniewasz, gdy nasz straznik "]},{"code":401,"indent":0,"parameters":["zginie to, po krutkim czasie się odradze "]},{"code":401,"indent":0,"parameters":["jeszcze silniejszy."]},{"code":101,"indent":0,"parameters":["",0,1,2]},{"code":401,"indent":0,"parameters":["\\auto \\msgevent[30] Więc jeżeli nie przekonasz "]},{"code":401,"indent":0,"parameters":["naszej szamanki aby upażyła ci naparm który pozwoli "]},{"code":401,"indent":0,"parameters":["ci przejść koło torena, TO NIGDNY Z TĄ NIE WYJDZIESZ"]},{"code":401,"indent":0,"parameters":["ŁACHACHA"]},{"code":101,"indent":0,"parameters":["",0,1,2]},{"code":401,"indent":0,"parameters":["\\auto \\msgevent[30] Ale się nie martw, jest bardzo miła"]},{"code":401,"indent":0,"parameters":[",więc będize dobrze."]},{"code":101,"indent":0,"parameters":["",0,1,2]},{"code":401,"indent":0,"parameters":["\\auto \\msgevent[30] To do zobaczenie potem."]},{"code":121,"indent":0,"parameters":[110,110,0]},{"code":0,"indent":0,"parameters":[]}],"name":"cat scenka puszcza","switchId":1,"trigger":0},
{"id":9,"list":[{"code":101,"indent":0,"parameters":["",0,1,0]},{"code":401,"indent":0,"parameters":["Wiadro jest zapełnione w \\V[26]0%"]},{"code":126,"indent":0,"parameters":[35,0,0,1]},{"code":0,"indent":0,"parameters":[]}],"name":"Wiadro","switchId":1,"trigger":0},
{"id":10,"list":[{"code":0,"indent":0,"parameters":[]}],"name":"","switchId":1,"trigger":0},
{"id":11,"list":[{"code":0,"indent":0,"parameters":[]}],"name":"------------------","switchId":1,"trigger":0},
{"id":12,"list":[{"code":111,"indent":0,"parameters":[0,3,0]},{"code":223,"indent":1,"parameters":[[-68,-68,0,68],1,false]},{"code":241,"indent":1,"parameters":[{"name":"Wiezienie_w_Nocy","volume":90,"pitch":100,"pan":0}]},{"code":0,"indent":1,"parameters":[]},{"code":411,"indent":0,"parameters":[]},{"code":223,"indent":1,"parameters":[[0,0,0,0],1,false]},{"code":241,"indent":1,"parameters":[{"name":"Wiezienie_w_Dzien","volume":90,"pitch":100,"pan":0}]},{"code":0,"indent":1,"parameters":[]},{"code":412,"indent":0,"parameters":[]},{"code":0,"indent":0,"parameters":[]}],"name":"W WIĘZIENIU","switchId":2,"trigger":2},
{"id":13,"list":[{"code":221,"indent":0,"parameters":[]},{"code":241,"indent":0,"parameters":[{"name":"","volume":90,"pitch":100,"pan":0}]},{"code":230,"indent":0,"parameters":[180]},{"code":250,"indent":0,"parameters":[{"name":"scenka_koncowa","volume":100,"pitch":100,"pan":0}]},{"code":261,"indent":0,"parameters":["UcieczkaWiezienie"]},{"code":230,"indent":0,"parameters":[60]},{"code":101,"indent":0,"parameters":["",0,2,0]},{"code":401,"indent":0,"parameters":["Koniec wersji Demo"]},{"code":230,"indent":0,"parameters":[60]},{"code":241,"indent":0,"parameters":[{"name":"napisy_koncowe","volume":90,"pitch":100,"pan":0}]},{"code":105,"indent":0,"parameters":[1,false]},{"code":405,"indent":0,"parameters":["Atorth: tales of Ulkimond"]},{"code":405,"indent":0,"parameters":["by. SzyrGameStudio"]},{"code":405,"indent":0,"parameters":[""]},{"code":405,"indent":0,"parameters":["Projektanci poziomów:"]},{"code":405,"indent":0,"parameters":["-DEVMASSYN"]},{"code":405,"indent":0,"parameters":["-Tymoteusz \"Togii\" Król"]},{"code":405,"indent":0,"parameters":["-Igor \"SzyRRogi\" Różanowski"]},{"code":405,"indent":0,"parameters":["-Eris"]},{"code":405,"indent":0,"parameters":[""]},{"code":405,"indent":0,"parameters":["Muzyka"]},{"code":405,"indent":0,"parameters":["-Kunner"]},{"code":405,"indent":0,"parameters":[""]},{"code":405,"indent":0,"parameters":["Grafika"]},{"code":405,"indent":0,"parameters":["-Jakub \"Qubuss\" Beben"]},{"code":405,"indent":0,"parameters":["-Hubert Sikorski"]},{"code":405,"indent":0,"parameters":["-Tymoteusz \"Togii\" Król"]},{"code":405,"indent":0,"parameters":[""]},{"code":405,"indent":0,"parameters":["Lore"]},{"code":405,"indent":0,"parameters":["-Szymon Kirszenstein"]},{"code":354,"indent":0,"parameters":[]},{"code":0,"indent":0,"parameters":[]}],"name":"Koniec Dema","switchId":1,"trigger":0}
]